{
  "version": "1.0.0-beta.2",
  "url": "https://github.com/Adamax-AI/anis-releases/releases/download/android-v1.0.0-beta.2/anis-1.0.0-beta.2-android.apk",
  "md5": "84319614101d852cd315b02eb15a6ca6",
  "notes": "\n- **الإبلاغ من شاشة السجل**: صار بإمكانك الإبلاغ عن أي تفريغ مباشرةً من بطاقات السجل، تمامًا كما في نسخة الكمبيوتر.\n- **إرسال أكثر من ملاحظة على التفريغ نفسه**: لم يعد زر الإبلاغ يُقفل بعد أول إرسال، فيمكنك إرسال أكثر من بلاغ أو ملاحظة على التفريغ ذاته.\n- **عرض أفضل على الأجهزة اللوحية والوضع الأفقي**: نافذة الإبلاغ والملاحظات صارت تظهر بحجم مناسب في المنتصف بدل أن تمتد على كامل عرض الشاشة، ولم تعد لوحة المفاتيح تحجب حقل الكتابة.\n- **بطاقات سجل أكثر ترتيبًا**: يظهر نص التفريغ مباشرةً، مع طيّ النصوص الطويلة إلى أربعة أسطر وزر \"عرض المزيد\" لتوسيعها عند الحاجة.\n\nUpdates: report a transcription directly from History cards; file more than one report or note on the same transcription (the report action no longer locks after the first send); the report and feedback dialog now sits centered at a sensible width on tablets and in landscape and is no longer covered by the soft keyboard; and tidier History cards that show the transcript text directly with a \"read more\" toggle for long entries.",
  "pub_date": "2026-07-17T16:10:51Z"
}
